Metadata-Version: 2.4
Name: carrotclient
Version: 0.2.0
Summary: This is a simple python module
Home-page: 
Author: CarrotClient
Author-email: suport@carrotclient.com
Classifier: Programming Language :: Python :: 3
Classifier: License :: OSI Approved :: MIT License
Classifier: Operating System :: OS Independent
Requires-Python: >=3.6
License-File: LICENSE
Dynamic: author
Dynamic: author-email
Dynamic: classifier
Dynamic: description
Dynamic: description-content-type
Dynamic: license-file
Dynamic: requires-python
Dynamic: summary
